mcp_filter/__init__.py
mcp_filter/cli.py
mcp_filter/config.py
mcp_filter/filter_server.py
mcp_filter/health.py
mcp_filter/logging.py
mcp_filter/upstream.py
mcp_filter/version.py
mcp_filter-0.1.0.dist-info/METADATA
mcp_filter-0.1.0.dist-info/WHEEL
mcp_filter-0.1.0.dist-info/entry_points.txt
mcp_filter-0.1.0.dist-info/licenses/LICENSE
mcp_filter-0.1.0.dist-info/RECORD
