Metadata-Version: 2.4
Name: mcp-filter
Version: 0.1.0
Summary: MCP server proxy that exposes a filtered tool surface from upstream servers.
Author: MCP Filter Contributors
License: MIT
License-File: LICENSE
Keywords: filter,mcp,model-context-protocol,proxy
Classifier: Development Status :: 4 - Beta
Classifier: Intended Audience :: Developers
Classifier: License :: OSI Approved :: MIT License
Classifier: Programming Language :: Python :: 3
Classifier: Programming Language :: Python :: 3.10
Classifier: Programming Language :: Python :: 3.11
Classifier: Programming Language :: Python :: 3.12
Requires-Python: >=3.10
Requires-Dist: fastmcp>=0.3.0
Requires-Dist: mcp>=1.0.0
Requires-Dist: pydantic>=2.5.0
Requires-Dist: rich>=13.0.0
Requires-Dist: typer>=0.12.0
Requires-Dist: uvloop>=0.19.0; platform_system != 'Windows'
Provides-Extra: dev
Requires-Dist: anyio>=4.0.0; extra == 'dev'
Requires-Dist: mypy>=1.8.0; extra == 'dev'
Requires-Dist: pytest-asyncio>=0.23.0; extra == 'dev'
Requires-Dist: pytest>=8.0.0; extra == 'dev'
Requires-Dist: ruff>=0.3.0; extra == 'dev'
